pydevops_proxy/__init__.py
pydevops_proxy/gitlab/__init__.py
opsas.gitlab-0.0.1.dist-info/METADATA
opsas.gitlab-0.0.1.dist-info/WHEEL
opsas.gitlab-0.0.1.dist-info/top_level.txt
opsas.gitlab-0.0.1.dist-info/RECORD
